<?xml version="1.0" encoding="UTF-8"?>
<databaseChangeLog
        xmlns:xsi="http://www.w3.org/2001/XMLSchema-instance"
        xmlns:ext="http://www.liquibase.org/xml/ns/dbchangelog-ext"
        xmlns="http://www.liquibase.org/xml/ns/dbchangelog"
        xsi:schemaLocation="http://www.liquibase.org/xml/ns/dbchangelog http://www.liquibase.org/xml/ns/dbchangelog/dbchangelog-3.1.xsd
    http://www.liquibase.org/xml/ns/dbchangelog-ext http://www.liquibase.org/xml/ns/dbchangelog/dbchangelog-ext.xsd">
    <changeSet author="admin" id="2">
        <insert tableName="user">
            <column name="id" valueNumeric="99"/>
            <column name="name" value="ROLE_ADMIN"/>
            <column name="username" value="admin9"/>
            <column name="password" value="$2a$10$.fYDZl1eFRUL5sApwlxvF.XDQmAXoxbROQRUFffUYGtxGDJzJyRVy"/>
        </insert>
                <insert tableName="user">
            <column name="id" valueNumeric="98"/>
            <column name="name" value="ROLE_USER"/>
            <column name="username" value="admin7"/>
            <column name="password" value="$2a$10$.fYDZl1eFRUL5sApwlxvF.XDQmAXoxbROQRUFffUYGtxGDJzJyRVy"/>
        </insert>
    </changeSet>
</databaseChangeLog>

<!-- abv123456 -->
<!-- $2a$10$Y/vffgJ9shcQ9Z4PhG3jvOLRo5K4UBjhTSl8wytpUJUis.YqQfshy -->
<!--  mai problema s povtorenata parola idva s registriraniq ot liquibase -->